Metadata-Version: 2.1
Name: mytracker-export-api
Version: 1.0.0
Summary: Python wrapper for MyTracker Export API.
Home-page: UNKNOWN
Author: Artyom Novopolsky
Author-email: a.novopolsky@corp.mail.ru
License: UNKNOWN
Platform: UNKNOWN
Requires-Python: >=3.8
License-File: LICENSE
